vulhub/__init__.py
vulhub/cli/__init__.py
vulhub/cli/base_cli.py
vulhub/cli/command.py
vulhub/cli/local_cli.py
vulhub/cli/main.py
vulhub/cli/remote_cli.py
vulhub/plugin/__init__.py
vulhub/plugin/huoxian_iast.py
vulhub_cli-0.0.6.dist-info/LICENSE
vulhub_cli-0.0.6.dist-info/METADATA
vulhub_cli-0.0.6.dist-info/WHEEL
vulhub_cli-0.0.6.dist-info/entry_points.txt
vulhub_cli-0.0.6.dist-info/top_level.txt
vulhub_cli-0.0.6.dist-info/RECORD
