Metadata-Version: 2.1
Name: vulhub-cli
Version: 0.0.6
Summary: easy command tool for vulhub
Home-page: https://www.huoxian.cn/
Author: Owefsad, Inc.
Author-email: dongzhiyong@huoxian.cn
License: MIT License
Project-URL: Source, https://github.com/huoxianclub/vulhub-compose
Project-URL: Tracker, https://github.com/huoxianclub/vulhub-compose/issues
Project-URL: VulHub, https://github.com/vulhub/vulhub
Project-URL: DongTai-IAST, http://iast.huoxian.cn:8000/
Project-URL: DongTai-Doc, https://hxsecurity.github.io/DongTaiDoc/#/doc/deploy/vulns
Platform: UNKNOWN
Classifier: Development Status :: 5 - Production/Stable
Classifier: Environment :: Console
Classifier: Intended Audience :: Developers
Classifier: License :: OSI Approved :: MIT License
Classifier: Programming Language :: Python :: 3
Classifier: Programming Language :: Python :: 3.4
Classifier: Programming Language :: Python :: 3.6
Classifier: Programming Language :: Python :: 3.7
Classifier: Programming Language :: Python :: 3.8
Classifier: Programming Language :: Python :: 3.9
Requires-Python: >=3.4
Requires-Dist: docker-compose (>=1.28.5)
Requires-Dist: fire (>=0.4.0)
Requires-Dist: backports.ssl-match-hostname (<4,>=3.5) ; python_version < "3.5"
Requires-Dist: colorama (<1,>=0.4) ; sys_platform == "win32"
